weather_atmas/_init_.py
weather_mi_zy-0.1.0.dist-info/licenses/LICENSE
weather_mi_zy-0.1.0.dist-info/METADATA
weather_mi_zy-0.1.0.dist-info/WHEEL
weather_mi_zy-0.1.0.dist-info/top_level.txt
weather_mi_zy-0.1.0.dist-info/RECORD
