Metadata-Version: 2.4
Name: weather-mi_zy
Version: 0.1.0
Summary: Add your description here
Requires-Python: >=3.12
License-File: LICENSE
Requires-Dist: httpx>=0.28.1
Requires-Dist: mcp[cli]>=1.4.1
Dynamic: license-file
